clij2_fft-0.29.data/data/Library/bin/clFFT.dll
clij2_fft-0.29.data/data/Library/bin/clij2fft.dll
clij2_fft-0.29.data/data/lib/libclFFT.2.dylib
clij2_fft-0.29.data/data/lib/libclFFT.so.2
clij2_fft-0.29.data/data/lib/libclij2fft.dylib
clij2_fft-0.29.data/data/lib/libclij2fft.so
clij2fft/__init__.py
clij2fft/libs.py
clij2fft/pad.py
clij2fft/print_info.py
clij2fft/richardson_lucy.py
clij2fft/richardson_lucy_dask.py
clij2_fft-0.29.dist-info/METADATA
clij2_fft-0.29.dist-info/WHEEL
clij2_fft-0.29.dist-info/top_level.txt
clij2_fft-0.29.dist-info/RECORD
