Metadata-Version: 2.4
Name: clij2-fft
Version: 0.29
Summary: A python wrapper around clij2 opencl FFT algorithms
Home-page: https://github.com/clij/clij2-fft
Author: Robert Haase, Brian Northan
Author-email: bnorthan@gmail.com
License: BSD
Requires-Dist: numpy
Requires-Dist: dask
Requires-Dist: dask-image
Requires-Dist: pyopencl
Dynamic: author
Dynamic: author-email
Dynamic: description
Dynamic: description-content-type
Dynamic: home-page
Dynamic: license
Dynamic: requires-dist
Dynamic: summary
